__init__.py
config.py
main.py
g4music_discord_rpc-1.0.2.dist-info/licenses/LICENSE
g4music_discord_rpc-1.0.2.dist-info/METADATA
g4music_discord_rpc-1.0.2.dist-info/WHEEL
g4music_discord_rpc-1.0.2.dist-info/entry_points.txt
g4music_discord_rpc-1.0.2.dist-info/top_level.txt
g4music_discord_rpc-1.0.2.dist-info/RECORD
