Metadata-Version: 2.4
Name: g4music-discord-rpc
Version: 1.0.2
Summary: Discord Rich Presence for g4music.
Author-email: Some1Rxndom <None@None.com>
License-Expression: MIT
Project-URL: Homepage, https://github.com/x-9917638/g4music-discord-rpc
Project-URL: Issues, https://github.com/x-9917638/g4music-discord-rpc/issues
Classifier: Programming Language :: Python :: 3
Classifier: Operating System :: Unix
Requires-Python: >=3.9
License-File: LICENSE
Requires-Dist: dbus-fast>=2.44.5
Requires-Dist: discord-rpc>=5.5
Requires-Dist: requests>=2.32.5
Requires-Dist: tomli_w>=1.2.0
Dynamic: license-file
